setup.cfg
setup.py
limone_zodb/__init__.py
limone_zodb/tests.py
limone_zodb.egg-info/PKG-INFO
limone_zodb.egg-info/SOURCES.txt
limone_zodb.egg-info/dependency_links.txt
limone_zodb.egg-info/entry_points.txt
limone_zodb.egg-info/not-zip-safe
limone_zodb.egg-info/requires.txt
limone_zodb.egg-info/top_level.txt