Metadata-Version: 1.0
Name: limone-zodb
Version: 0.1a1
Summary: ZODB persistence for Limone content types.
Home-page: http://pylonsproject.org
Author: Chris Rossi, Archimedean Company
Author-email: pylons-devel@googlegroups.com
License: BSD-derived (http://www.repoze.org/LICENSE.txt)
Platform: UNKNOWN
Classifier: Intended Audience :: Developers
Classifier: Programming Language :: Python
Classifier: Framework :: Pylons
Classifier: License :: Repoze Public License
